{
  "watchlist": [
    "RDW",
    "TSLA.NE",
    "AMD.NE",
    "UNH.NE",
    "VDY.TO",
    "TSLL",
    "TSLU.TO",
    "NVDA.NE",
    "QMCO",
    "RKLB",
    "GOOG.NE",
    "TSLA",
    "META.NE",
    "OSCR",
    "SMCI.NE",
    "ASML.NE",
    "AMZN.NE",
    "PLTR.NE",
    "MSFT.NE",
    "SMCL",
    "AMD",
    "QBTS",
    "ASTS",
    "VFV.TO",
    "ORCL",
    "IONQ",
    "AAPL.NE",
    "KULR",
    "AVGO.NE",
    "IBM.NE",
    "XE",
    "LULU.NE",
    "DVLT",
    "RBLX",
    "NFLX.NE",
    "AMZU",
    "LAES",
    "CLSK",
    "NOK",
    "ORCX",
    "ETHU"
  ],
  "watchlistGroups": [
    {
      "id": "default",
      "name": "Watchlist",
      "symbols": [
        "TSLA.NE",
        "AMD.NE",
        "RDW",
        "UNH.NE",
        "VDY.TO",
        "TSLL",
        "TSLU.TO",
        "NVDA.NE",
        "QMCO",
        "RKLB",
        "GOOG.NE",
        "TSLA",
        "META.NE",
        "OSCR",
        "SMCI.NE",
        "ASML.NE",
        "AMZN.NE",
        "PLTR.NE",
        "MSFT.NE",
        "SMCL",
        "AMD",
        "QBTS",
        "ASTS",
        "VFV.TO",
        "ORCL",
        "IONQ",
        "AAPL.NE",
        "KULR",
        "AVGO.NE",
        "IBM.NE",
        "XE",
        "LULU.NE",
        "DVLT",
        "RBLX",
        "NFLX.NE",
        "AMZU",
        "LAES",
        "CLSK",
        "NOK",
        "ORCX",
        "ETHU"
      ]
    }
  ],
  "trades": [
    {
      "price": 7.97,
      "shares": 150,
      "date": "2026-03-30T16:01:00.000Z",
      "note": "",
      "side": "BUY",
      "symbol": "RDW",
      "id": "1780603334657-i6dxa8l"
    },
    {
      "price": 33.81,
      "shares": 309.9,
      "date": "2026-04-15T16:03:00.000Z",
      "note": "",
      "side": "BUY",
      "symbol": "TSLA.NE",
      "id": "1780603402025-uhyyoha"
    },
    {
      "price": 38.19,
      "shares": 156.5941,
      "date": "2026-04-02T16:04:00.000Z",
      "note": "",
      "side": "BUY",
      "symbol": "AMD.NE",
      "id": "1780603459491-tqkgr2z"
    },
    {
      "price": 13.7,
      "shares": 317.894,
      "date": "2026-01-27T17:20:00.000Z",
      "note": "",
      "id": "1780604444765-proqj8g",
      "side": "BUY",
      "symbol": "UNH.NE"
    },
    {
      "price": 65.04,
      "shares": 176.6649,
      "date": "2026-02-12T17:21:00.000Z",
      "note": "",
      "id": "1780604487200-k91r7hp",
      "side": "BUY",
      "symbol": "VDY.TO"
    },
    {
      "price": 12.72,
      "shares": 490,
      "date": "2026-03-26T16:25:00.000Z",
      "note": "",
      "id": "1780604728361-0ypmktf",
      "side": "BUY",
      "symbol": "TSLL"
    },
    {
      "price": 27.28,
      "shares": 392.3488,
      "date": "2026-01-22T17:26:00.000Z",
      "note": "",
      "id": "1780604807529-wzh92jo",
      "side": "BUY",
      "symbol": "TSLU.TO"
    },
    {
      "price": 41.61,
      "shares": 133,
      "date": "2026-04-10T18:29:00.000Z",
      "note": "",
      "id": "1780604970924-amz8i61",
      "side": "BUY",
      "symbol": "NVDA.NE"
    },
    {
      "price": 9.29,
      "shares": 191,
      "date": "2026-05-06T17:29:00.000Z",
      "note": "",
      "id": "1780605012589-jom8u9e",
      "side": "BUY",
      "symbol": "QMCO"
    },
    {
      "price": 47.98,
      "shares": 25,
      "date": "2025-08-29T18:30:00.000Z",
      "note": "",
      "id": "1780605068005-3ma7hsn",
      "side": "BUY",
      "symbol": "RKLB"
    },
    {
      "price": 49,
      "shares": 61.0095,
      "date": "2026-02-19T21:32:00.000Z",
      "note": "",
      "id": "1780605134104-hyipty4",
      "side": "BUY",
      "symbol": "GOOG.NE"
    },
    {
      "price": 427.15,
      "shares": 5.4794,
      "date": "2026-02-03T21:32:00.000Z",
      "note": "",
      "id": "1780605174440-blusltx",
      "side": "BUY",
      "symbol": "TSLA"
    },
    {
      "price": 36.02,
      "shares": 92.6658,
      "date": "2026-04-24T20:33:00.000Z",
      "note": "",
      "id": "1780605220249-68uhuz0",
      "side": "BUY",
      "symbol": "META.NE"
    },
    {
      "price": 16.22,
      "shares": 90,
      "date": "2026-04-20T20:34:00.000Z",
      "note": "",
      "id": "1780605262952-1otoyoh",
      "side": "BUY",
      "symbol": "OSCR"
    },
    {
      "price": 13.23,
      "shares": 191.5637,
      "date": "2026-05-28T20:34:00.000Z",
      "note": "",
      "id": "1780605312212-ai1hofu",
      "side": "BUY",
      "symbol": "SMCI.NE"
    },
    {
      "price": 19.75,
      "shares": 50.0881,
      "date": "2025-08-07T20:35:00.000Z",
      "note": "",
      "id": "1780605376862-m1o17az",
      "side": "BUY",
      "symbol": "ASML.NE"
    },
    {
      "price": 24.86,
      "shares": 70,
      "date": "2025-06-05T20:36:00.000Z",
      "note": "",
      "id": "1780605429885-urp23f9",
      "side": "BUY",
      "symbol": "AMZN.NE"
    },
    {
      "price": 13.46,
      "shares": 160,
      "date": "2025-11-13T21:37:00.000Z",
      "note": "",
      "id": "1780605473925-k8m0bo1",
      "side": "BUY",
      "symbol": "PLTR.NE"
    },
    {
      "price": 203.23,
      "shares": 9,
      "date": "2025-05-13T00:46:00.000Z",
      "note": "",
      "id": "1780620434315-dtdc46m",
      "side": "BUY",
      "symbol": "SMCL"
    },
    {
      "price": 210.77,
      "shares": 2,
      "date": "2026-01-09T01:47:00.000Z",
      "note": "",
      "id": "1780620476613-fdbn1jl",
      "side": "BUY",
      "symbol": "AMD"
    },
    {
      "price": 32.03,
      "shares": 30,
      "date": "2025-10-04T00:48:00.000Z",
      "note": "",
      "id": "1780620502038-dzgfli9",
      "side": "BUY",
      "symbol": "QBTS"
    },
    {
      "price": 74.37,
      "shares": 7,
      "date": "2026-06-05T00:48:00.000Z",
      "note": "",
      "id": "1780620520641-hhh1f8t",
      "side": "BUY",
      "symbol": "ASTS"
    },
    {
      "price": 178.87,
      "shares": 5.2151,
      "date": "2026-05-13T00:48:00.000Z",
      "note": "",
      "id": "1780620556551-73a4qdy",
      "side": "BUY",
      "symbol": "VFV.TO"
    },
    {
      "price": 189.67,
      "shares": 3,
      "date": "2026-01-16T01:49:00.000Z",
      "note": "",
      "id": "1780620578542-n9hh7mm",
      "side": "BUY",
      "symbol": "ORCL"
    },
    {
      "price": 57.41,
      "shares": 10,
      "date": "2025-10-24T00:49:00.000Z",
      "note": "",
      "id": "1780620607418-jrvdsiv",
      "side": "BUY",
      "symbol": "IONQ"
    },
    {
      "price": 38.51,
      "shares": 20,
      "date": "2026-04-18T00:50:00.000Z",
      "note": "",
      "id": "1780620639323-xtan4ws",
      "side": "BUY",
      "symbol": "AAPL.NE"
    },
    {
      "price": 3.54,
      "shares": 130,
      "date": "2026-01-13T01:50:00.000Z",
      "note": "",
      "id": "1780620658113-c1vsusx",
      "side": "BUY",
      "symbol": "KULR"
    },
    {
      "price": 15.86,
      "shares": 49,
      "date": "2026-06-05T00:51:00.000Z",
      "note": "",
      "id": "1780620683766-ws8qhok",
      "side": "BUY",
      "symbol": "AVGO.NE"
    },
    {
      "price": 46.77,
      "shares": 15,
      "date": "2026-06-03T00:51:00.000Z",
      "note": "",
      "id": "1780620708952-qaduoqc",
      "side": "BUY",
      "symbol": "IBM.NE"
    },
    {
      "price": 28.85,
      "shares": 20,
      "date": "2026-05-28T00:51:00.000Z",
      "note": "",
      "id": "1780620727088-5yb8dw8",
      "side": "BUY",
      "symbol": "XE"
    },
    {
      "price": 10.6,
      "shares": 120,
      "date": "2025-07-03T00:52:00.000Z",
      "note": "",
      "id": "1780620751267-zthu069",
      "side": "BUY",
      "symbol": "LULU.NE"
    },
    {
      "price": 1.49,
      "shares": 990.9855,
      "date": "2025-10-07T00:52:00.000Z",
      "note": "",
      "id": "1780620776300-an3gw3g",
      "side": "BUY",
      "symbol": "DVLT"
    },
    {
      "price": 93.49,
      "shares": 10,
      "date": "2025-06-10T00:53:00.000Z",
      "note": "",
      "id": "1780620814973-6dt5y0x",
      "side": "BUY",
      "symbol": "RBLX"
    },
    {
      "price": 36.82,
      "shares": 18,
      "date": "2025-12-18T01:53:00.000Z",
      "note": "",
      "id": "1780620842482-q9z1pko",
      "side": "BUY",
      "symbol": "NFLX.NE"
    },
    {
      "price": 36.2,
      "shares": 10,
      "date": "2025-11-26T01:54:00.000Z",
      "note": "",
      "id": "1780620872976-97zxfra",
      "side": "BUY",
      "symbol": "AMZU"
    },
    {
      "price": 5.02,
      "shares": 96.8593,
      "date": "2025-10-07T00:54:00.000Z",
      "note": "",
      "id": "1780620895548-s6f1nkc",
      "side": "BUY",
      "symbol": "LAES"
    },
    {
      "price": 12.09,
      "shares": 20,
      "date": "2026-01-14T01:55:00.000Z",
      "note": "",
      "id": "1780620933336-d0b8wkd",
      "side": "BUY",
      "symbol": "CLSK"
    },
    {
      "price": 15.74,
      "shares": 20,
      "date": "2026-05-23T00:55:00.000Z",
      "note": "",
      "id": "1780620954669-tx6o7an",
      "side": "BUY",
      "symbol": "NOK"
    },
    {
      "price": 75.8,
      "shares": 5,
      "date": "2025-06-21T00:56:00.000Z",
      "note": "",
      "id": "1780620976148-ymuygzw",
      "side": "BUY",
      "symbol": "ORCX"
    },
    {
      "price": 74.48,
      "shares": 18.0182,
      "date": "2025-11-05T01:56:00.000Z",
      "note": "",
      "id": "1780621003789-xugqbtc",
      "side": "BUY",
      "symbol": "ETHU"
    }
  ],
  "plannedOrders": [],
  "settings": {
    "marketDataProvider": "yahoo",
    "marketDataProviderChosen": true,
    "yahooProxyUrl": "https://trademarker-yahoo-proxy.kunp-xu.workers.dev",
    "githubOwner": "kunpengxu",
    "githubRepo": "TradeMarker",
    "githubBranch": "main",
    "githubDataPath": "data/trademarker.json"
  },
  "updatedAt": "2026-06-05T00:56:43.789Z"
}